airflow_provider_nessie/__init__.py
airflow_provider_nessie/example_dags/basic_nessie.py
airflow_provider_nessie/example_dags/spark_nessie_iceberg.py
airflow_provider_nessie/hooks/__init__.py
airflow_provider_nessie/hooks/nessie_hook.py
airflow_provider_nessie/operators/__init__.py
airflow_provider_nessie/operators/commit_operator.py
airflow_provider_nessie/operators/create_branch_operator.py
airflow_provider_nessie/operators/delete_branch_operator.py
airflow_provider_nessie/operators/merge_branch_operator.py
airflow_provider_nessie-0.1.2.dist-info/entry_points.txt
airflow_provider_nessie-0.1.2.dist-info/LICENSE
airflow_provider_nessie-0.1.2.dist-info/WHEEL
airflow_provider_nessie-0.1.2.dist-info/METADATA
airflow_provider_nessie-0.1.2.dist-info/RECORD
