Metadata-Version: 2.1
Name: airflow-provider-nessie
Version: 0.1.2
Summary: Entry point for the Nessie Airflow provider.
Home-page: https://github.com/projectnessie/nessie_provider
Author: Project Nessie
Author-email: nessie-release-builder@dremio.com
Requires-Python: >=3.6
Classifier: Programming Language :: Python :: 3.6
Classifier: Programming Language :: Python :: 3.7
Classifier: Programming Language :: Python :: 3.8
Classifier: Programming Language :: Python :: 3.9
Classifier: Programming Language :: Python :: 3 :: Only
Requires-Dist: pynessie==0.8.3
Project-URL: Documentation, https://projectnessie.github.io/nessie_provider
